{
    "version": "72.0.3779.0",
    "description": "Fast, secure, easy-to-use browser.",
    "homepage": "https://www.opera.com/",
    "license": {
        "identifier": "Freeware",
        "url": "https://www.opera.com/eula/computers"
    },
    "architecture": {
        "64bit": {
            "url": "https://download1.operacdn.com/pub/opera-developer/72.0.3779.0/win/Opera_Developer_72.0.3779.0_Setup_x64.exe#/dl.7z",
            "hash": "187692f36887dee95a4b2033198c51f12022f6486a5f333a3f86bb33af760db4"
        },
        "32bit": {
            "url": "https://download1.operacdn.com/pub/opera-developer/72.0.3779.0/win/Opera_Developer_72.0.3779.0_Setup.exe#/dl.7z",
            "hash": "5a3ff29dcc52a875a894bd4e1c67be47c5e3fddeee750ebb66ddd81b4029e938"
        }
    },
    "installer": {
        "script": [
            "Remove-Item -Path \"$dir\\*_list\" -Force",
            "Move-Item -Path \"$dir\\*\" -Destination \"$dir\\$version\" -Exclude 'Assets', 'launcher*', 'Resources.pri' -ErrorAction Ignore",
            "if (!(Test-Path \"$dir\\$version\\localization\")) {",
            "   New-Item -Path \"$dir\\$version\\localization\" -ItemType Directory | Out-Null",
            "   Move-Item -Path \"$dir\\$version\\*.pak\" -Destination \"$dir\\$version\\localization\" -Exclude 'opera*' -ErrorAction Ignore",
            "}",
            "Set-Content -Path \"$dir\\installer_prefs.json\" -Value (@{ 'autoupdate'= $false; 'enable_stats' = $false; 'single_profile' = $true } | ConvertTo-Json) -Encoding ASCII"
        ]
    },
    "shortcuts": [
        [
            "launcher.exe",
            "Opera Developer"
        ]
    ],
    "persist": "profile",
    "checkver": {
        "url": "http://get.opera.com/ftp/pub/opera-developer/",
        "regex": "([\\d.]+)/",
        "reverse": true
    },
    "autoupdate": {
        "architecture": {
            "64bit": {
                "url": "https://download1.operacdn.com/pub/opera-developer/$version/win/Opera_Developer_$version_Setup_x64.exe#/dl.7z"
            },
            "32bit": {
                "url": "https://download1.operacdn.com/pub/opera-developer/$version/win/Opera_Developer_$version_Setup.exe#/dl.7z"
            }
        },
        "hash": {
            "url": "$url.sha256sum"
        }
    }
}
