{
    "version": "10.4.3.793",
    "description": "Clean junks of Browsers, remove junk and useless files of Windows and Defragment your disk.",
    "homepage": "https://www.wisecleaner.com/wise-disk-cleaner.html",
    "license": "Freeware",
    "url": "http://downloads.wisecleaner.com/soft/WDCFree_10.4.3.793.zip",
    "hash": "8dd4f15527b2f9a17f182b3a3b35fd7376d9090d0cbe3f891661992ae5d93a73",
    "extract_dir": "Wise Disk Cleaner",
    "shortcuts": [
        [
            "WiseDiskCleaner.exe",
            "Wise Disk Cleaner"
        ]
    ],
    "persist": [
        "config.ini",
        "DefragOptions.ini"
    ],
    "checkver": {
        "url": "https://www.wisecleaner.com/download.html",
        "regex": "WDCFree.+?([\\d.]+)?\\.zip"
    },
    "autoupdate": {
        "url": "http://downloads.wisecleaner.com/soft/WDCFree_$version.zip"
    }
}
