{
    "version": "5.7.0",
    "description": "Video and audio conferencing, chat, and webinars",
    "homepage": "https://zoom.us",
    "license": {
        "identifier": "Shareware",
        "url": "https://zoom.us/terms"
    },
    "url": "https://www.zoom.us/client/latest/ZoomInstaller.exe#/dl.7z",
    "hash": "735644a1a7c5e71484737db0f5b379c6494bde920297f786fcc1f05f65a0425e",
    "pre_install": [
        "Expand-7zipArchive \"$dir\\Zoom.msi\" -Removal",
        "Remove-Item \"$dir\\Install*\""
    ],
    "shortcuts": [
        [
            "Zoom.exe",
            "Zoom"
        ]
    ],
    "checkver": {
        "url": "https://www.zoom.us/download",
        "regex": "Version ([\\d.]+)"
    },
    "autoupdate": {
        "url": "https://www.zoom.us/client/latest/ZoomInstaller.exe#/dl.7z"
    }
}
